{
    "prepare_queue": {
        "installed": [],
        "uninstalled": []
    },
    "config_munge": {
        "files": {
            "package.windows.appxmanifest": {
                "parents": {
                    "/Package/Capabilities": [
                        {
                            "xml": "<Capability Name=\"picturesLibrary\" />",
                            "count": 1
                        },
                        {
                            "xml": "<DeviceCapability Name=\"webcam\" />",
                            "count": 1
                        }
                    ]
                }
            },
            "package.windows80.appxmanifest": {
                "parents": {
                    "/Package/Capabilities": [
                        {
                            "xml": "<Capability Name=\"picturesLibrary\" />",
                            "count": 1
                        },
                        {
                            "xml": "<DeviceCapability Name=\"webcam\" />",
                            "count": 1
                        }
                    ]
                }
            },
            "package.phone.appxmanifest": {
                "parents": {
                    "/Package/Capabilities": [
                        {
                            "xml": "<Capability Name=\"picturesLibrary\" />",
                            "count": 1
                        },
                        {
                            "xml": "<DeviceCapability Name=\"webcam\" />",
                            "count": 1
                        }
                    ]
                }
            }
        }
    },
    "installed_plugins": {
        "com.microsoft.azure-mobile-services": {
            "PACKAGE_NAME": "Azure_Storage"
        },
        "org.apache.cordova.camera": {
            "PACKAGE_NAME": "Azure_Storage"
        },
        "org.apache.cordova.console": {
            "PACKAGE_NAME": "Azure_Storage"
        },
        "org.apache.cordova.device": {
            "PACKAGE_NAME": "Azure_Storage"
        },
        "org.apache.cordova.file": {
            "PACKAGE_NAME": "Azure_Storage"
        }
    },
    "dependent_plugins": {
        "org.apache.cordova.inappbrowser": {
            "PACKAGE_NAME": "Azure_Storage"
        }
    }
}